cleverchuk/engine/__init__.py
cleverchuk/engine/engine.py
cleverchuk/engine/scorer.py
cleverchuk/lib/__init__.py
cleverchuk/lib/algorithm.py
cleverchuk/lib/codec.py
cleverchuk/lib/dstructures.py
cleverchuk/lib/fs.py
cleverchuk/lib/indexing.py
cleverchuk/lib/lexers.py
cleverchuk_search_engine-0.0.4.dist-info/LICENSE
cleverchuk_search_engine-0.0.4.dist-info/METADATA
cleverchuk_search_engine-0.0.4.dist-info/WHEEL
cleverchuk_search_engine-0.0.4.dist-info/top_level.txt
cleverchuk_search_engine-0.0.4.dist-info/RECORD
