Metadata-Version: 2.1
Name: cleverchuk-search-engine
Version: 0.0.4
Summary: simple and extensible search engine backend
Requires-Python: >=3.10
License-File: LICENSE
Requires-Dist: nltk
Requires-Dist: sklearn
